potrace/__init__.py
potrace/_potrace.cp310-win_amd64.pyd
potrace/bezier.cp310-win_amd64.pyd
potrace/agg/__init__.py
potrace/agg/curves.cp310-win_amd64.pyd
tests/__init__.py
tests/test_basic.py
tests/test_bezier.py
tests/potrace/__init__.py
tests/potrace/agg/__init__.py
pypotrace_windows-0.2.dist-info/LICENSE
pypotrace_windows-0.2.dist-info/METADATA
pypotrace_windows-0.2.dist-info/WHEEL
pypotrace_windows-0.2.dist-info/top_level.txt
pypotrace_windows-0.2.dist-info/RECORD
