Metadata-Version: 2.1
Name: pypotrace-windows
Version: 0.2
Summary: potrace Python bindings. Compiled for windows
Home-page: http://github.com/dafne-imaging/pypotrace-windows
Author: Francesco Santini
Author-email: francesco.santini@gmail.com
License: UNKNOWN
Keywords: potrace bitmap vector graphics
Platform: UNKNOWN
Classifier: Development Status :: 4 - Beta
Classifier: Environment :: Console
Classifier: Intended Audience :: Developers
Classifier: License :: OSI Approved :: GNU General Public License (GPL)
Classifier: Natural Language :: English
Classifier: Operating System :: OS Independent
Classifier: Programming Language :: Cython
Classifier: Programming Language :: Python
Classifier: Topic :: Software Development :: Libraries :: Python Modules
Classifier: Topic :: Multimedia :: Graphics :: Graphics Conversion
License-File: LICENSE
Requires-Dist: numpy
Provides-Extra: dev
Requires-Dist: nose ; extra == 'dev'
Requires-Dist: pillow ; extra == 'dev'
Requires-Dist: cython (<0.29) ; extra == 'dev'
